[
  {
    "description": "",
    "elements": [
      {
        "description": "",
        "id": "hu02---detalle-de-álbumes;hu02---abrir-detalle-del-primer-álbum",
        "keyword": "Scenario",
        "line": 6,
        "name": "HU02 - Abrir detalle del primer álbum",
        "steps": [
          {
            "keyword": "Before",
            "hidden": true,
            "result": {
              "status": "passed",
              "duration": 9106436200
            }
          },
          {
            "arguments": [],
            "keyword": "Given ",
            "line": 4,
            "name": "the app is launched",
            "match": {
              "location": "features\\step_definitions\\albums.steps.js:6"
            },
            "result": {
              "status": "passed",
              "duration": 120607499
            }
          },
          {
            "arguments": [],
            "keyword": "When ",
            "line": 7,
            "name": "I tap the first album in the list",
            "match": {
              "location": "features\\step_definitions\\albums.steps.js:35"
            },
            "result": {
              "status": "passed",
              "duration": 242971000
            }
          },
          {
            "arguments": [],
            "keyword": "Then ",
            "line": 8,
            "name": "I should see the album name \"Buscando América\"",
            "match": {
              "location": "features\\step_definitions\\albums.steps.js:54"
            },
            "result": {
              "status": "passed",
              "duration": 876721299
            }
          },
          {
            "arguments": [],
            "keyword": "And ",
            "line": 9,
            "name": "I should see the album description",
            "match": {
              "location": "features\\step_definitions\\albums.steps.js:79"
            },
            "result": {
              "status": "passed",
              "duration": 92998200
            }
          },
          {
            "arguments": [],
            "keyword": "And ",
            "line": 10,
            "name": "I should see the album tracks section",
            "match": {
              "location": "features\\step_definitions\\albums.steps.js:87"
            },
            "result": {
              "status": "passed",
              "duration": 6666978999
            }
          },
          {
            "keyword": "After",
            "hidden": true,
            "result": {
              "status": "passed",
              "duration": 1214323499
            }
          }
        ],
        "tags": [],
        "type": "scenario"
      }
    ],
    "id": "hu02---detalle-de-álbumes",
    "line": 1,
    "keyword": "Feature",
    "name": "HU02 - Detalle de Álbumes",
    "tags": [],
    "uri": "features\\album_detail.feature"
  },
  {
    "description": "",
    "elements": [
      {
        "description": "",
        "id": "hu01---álbumes-lista;hu01---ver-la-lista-de-álbumes",
        "keyword": "Scenario",
        "line": 6,
        "name": "HU01 - Ver la lista de álbumes",
        "steps": [
          {
            "keyword": "Before",
            "hidden": true,
            "result": {
              "status": "passed",
              "duration": 8300907599
            }
          },
          {
            "arguments": [],
            "keyword": "Given ",
            "line": 4,
            "name": "the app is launched",
            "match": {
              "location": "features\\step_definitions\\albums.steps.js:6"
            },
            "result": {
              "status": "passed",
              "duration": 121146499
            }
          },
          {
            "arguments": [],
            "keyword": "Then ",
            "line": 7,
            "name": "I should see the albums list",
            "match": {
              "location": "features\\step_definitions\\albums.steps.js:29"
            },
            "result": {
              "status": "passed",
              "duration": 115206900
            }
          },
          {
            "keyword": "After",
            "hidden": true,
            "result": {
              "status": "passed",
              "duration": 862608399
            }
          }
        ],
        "tags": [],
        "type": "scenario"
      }
    ],
    "id": "hu01---álbumes-lista",
    "line": 1,
    "keyword": "Feature",
    "name": "HU01 - Álbumes lista",
    "tags": [],
    "uri": "features\\albums.feature"
  },
  {
    "description": "",
    "elements": [
      {
        "description": "",
        "id": "hu07---crear-album;hu07---crear-un-nuevo-album",
        "keyword": "Scenario",
        "line": 7,
        "name": "HU07 - Crear un nuevo album",
        "steps": [
          {
            "keyword": "Before",
            "hidden": true,
            "result": {
              "status": "passed",
              "duration": 8454220300
            }
          },
          {
            "arguments": [],
            "keyword": "Given ",
            "line": 4,
            "name": "the app is launched",
            "match": {
              "location": "features\\step_definitions\\albums.steps.js:6"
            },
            "result": {
              "status": "passed",
              "duration": 120014600
            }
          },
          {
            "arguments": [],
            "keyword": "When ",
            "line": 8,
            "name": "I tap the create album button",
            "match": {
              "location": "features\\step_definitions\\album_create.steps.js:125"
            },
            "result": {
              "status": "passed",
              "duration": 672500800
            }
          },
          {
            "arguments": [],
            "keyword": "And ",
            "line": 9,
            "name": "I fill the album creation form",
            "match": {
              "location": "features\\step_definitions\\album_create.steps.js:134"
            },
            "result": {
              "status": "passed",
              "duration": 122363732400
            }
          },
          {
            "arguments": [],
            "keyword": "And ",
            "line": 10,
            "name": "I submit the album creation form",
            "match": {
              "location": "features\\step_definitions\\album_create.steps.js:399"
            },
            "result": {
              "status": "passed",
              "duration": 1133443100
            }
          },
          {
            "arguments": [],
            "keyword": "Then ",
            "line": 11,
            "name": "I should see the album name \"Buscando América Prueba\"",
            "match": {
              "location": "features\\step_definitions\\albums.steps.js:54"
            },
            "result": {
              "status": "passed",
              "duration": 79416100
            }
          },
          {
            "keyword": "After",
            "hidden": true,
            "result": {
              "status": "passed",
              "duration": 1304885500
            }
          }
        ],
        "tags": [],
        "type": "scenario"
      }
    ],
    "id": "hu07---crear-album",
    "line": 1,
    "keyword": "Feature",
    "name": "HU07 - Crear Album",
    "tags": [],
    "uri": "features\\albums_create.feature"
  },
  {
    "description": "  Como usuario quiero ver la lista de coleccionistas para poder explorar perfiles",
    "elements": [
      {
        "description": "",
        "id": "hu05---listar-coleccionistas;ver-la-lista-de-coleccionistas",
        "keyword": "Scenario",
        "line": 7,
        "name": "Ver la lista de coleccionistas",
        "steps": [
          {
            "keyword": "Before",
            "hidden": true,
            "result": {
              "status": "passed",
              "duration": 9240493699
            }
          },
          {
            "arguments": [],
            "keyword": "Given ",
            "line": 5,
            "name": "the app is launched",
            "match": {
              "location": "features\\step_definitions\\albums.steps.js:6"
            },
            "result": {
              "status": "passed",
              "duration": 119440399
            }
          },
          {
            "arguments": [],
            "keyword": "Then ",
            "line": 8,
            "name": "I should see the collectors list",
            "match": {
              "location": "features\\step_definitions\\collectors.steps.js:26"
            },
            "result": {
              "status": "passed",
              "duration": 11422366100
            }
          },
          {
            "keyword": "After",
            "hidden": true,
            "result": {
              "status": "passed",
              "duration": 870662500
            }
          }
        ],
        "tags": [],
        "type": "scenario"
      }
    ],
    "id": "hu05---listar-coleccionistas",
    "line": 1,
    "keyword": "Feature",
    "name": "HU05 - listar coleccionistas",
    "tags": [],
    "uri": "features\\collectors.feature"
  },
  {
    "description": "",
    "elements": [
      {
        "description": "",
        "id": "hu04---detalle-de-artista;hu04---abrir-detalle-del-primer-artista",
        "keyword": "Scenario",
        "line": 6,
        "name": "HU04 - Abrir detalle del primer artista",
        "steps": [
          {
            "keyword": "Before",
            "hidden": true,
            "result": {
              "status": "passed",
              "duration": 8312231599
            }
          },
          {
            "arguments": [],
            "keyword": "Given ",
            "line": 4,
            "name": "the app is launched",
            "match": {
              "location": "features\\step_definitions\\albums.steps.js:6"
            },
            "result": {
              "status": "passed",
              "duration": 124499400
            }
          },
          {
            "arguments": [],
            "keyword": "When ",
            "line": 7,
            "name": "I tap Artist menu",
            "match": {
              "location": "features\\step_definitions\\musician_detail.steps.js:29"
            },
            "result": {
              "status": "passed",
              "duration": 1241760899
            }
          },
          {
            "arguments": [],
            "keyword": "And ",
            "line": 8,
            "name": "I tap the first artist in the list",
            "match": {
              "location": "features\\step_definitions\\musician_detail.steps.js:43"
            },
            "result": {
              "status": "passed",
              "duration": 10316261299
            }
          },
          {
            "arguments": [],
            "keyword": "Then ",
            "line": 9,
            "name": "I should see the artist name \"Demo Artist\"",
            "match": {
              "location": "features\\step_definitions\\musician_detail.steps.js:68"
            },
            "result": {
              "status": "passed",
              "duration": 788530700
            }
          },
          {
            "arguments": [],
            "keyword": "And ",
            "line": 10,
            "name": "I should see the artist description",
            "match": {
              "location": "features\\step_definitions\\musician_detail.steps.js:91"
            },
            "result": {
              "status": "passed",
              "duration": 89794299
            }
          },
          {
            "arguments": [],
            "keyword": "And ",
            "line": 11,
            "name": "I should see the artist albums section",
            "match": {
              "location": "features\\step_definitions\\musician_detail.steps.js:99"
            },
            "result": {
              "status": "passed",
              "duration": 190148399
            }
          },
          {
            "arguments": [],
            "keyword": "And ",
            "line": 12,
            "name": "I should see the artist prizes section",
            "match": {
              "location": "features\\step_definitions\\musician_detail.steps.js:126"
            },
            "result": {
              "status": "passed",
              "duration": 10190729200
            }
          },
          {
            "keyword": "After",
            "hidden": true,
            "result": {
              "status": "passed",
              "duration": 899972300
            }
          }
        ],
        "tags": [],
        "type": "scenario"
      }
    ],
    "id": "hu04---detalle-de-artista",
    "line": 1,
    "keyword": "Feature",
    "name": "HU04 - Detalle de Artista",
    "tags": [],
    "uri": "features\\musician_detail.feature"
  },
  {
    "description": "",
    "elements": [
      {
        "description": "",
        "id": "hu03---artistas-(musicians)-lista-y-detalle;ver-la-lista-de-artistas",
        "keyword": "Scenario",
        "line": 6,
        "name": "Ver la lista de artistas",
        "steps": [
          {
            "keyword": "Before",
            "hidden": true,
            "result": {
              "status": "passed",
              "duration": 8391487400
            }
          },
          {
            "arguments": [],
            "keyword": "Given ",
            "line": 4,
            "name": "the app is launched",
            "match": {
              "location": "features\\step_definitions\\albums.steps.js:6"
            },
            "result": {
              "status": "passed",
              "duration": 115501499
            }
          },
          {
            "arguments": [],
            "keyword": "Then ",
            "line": 7,
            "name": "I should see the musicians list",
            "match": {
              "location": "features\\step_definitions\\musicians.steps.js:19"
            },
            "result": {
              "status": "passed",
              "duration": 10555424400
            }
          },
          {
            "keyword": "After",
            "hidden": true,
            "result": {
              "status": "passed",
              "duration": 920549700
            }
          }
        ],
        "tags": [],
        "type": "scenario"
      }
    ],
    "id": "hu03---artistas-(musicians)-lista-y-detalle",
    "line": 1,
    "keyword": "Feature",
    "name": "HU03 - Artistas (Musicians) lista y detalle",
    "tags": [],
    "uri": "features\\musicians.feature"
  },
  {
    "description": "",
    "elements": [
      {
        "description": "",
        "id": "hu08---álbumes-lista-y-detalle;hu08---crear-un-track-desde-el-álbum",
        "keyword": "Scenario",
        "line": 6,
        "name": "HU08 - Crear un track desde el álbum",
        "steps": [
          {
            "keyword": "Before",
            "hidden": true,
            "result": {
              "status": "passed",
              "duration": 8457549700
            }
          },
          {
            "arguments": [],
            "keyword": "Given ",
            "line": 4,
            "name": "the app is launched",
            "match": {
              "location": "features\\step_definitions\\albums.steps.js:6"
            },
            "result": {
              "status": "passed",
              "duration": 121459999
            }
          },
          {
            "arguments": [],
            "keyword": "When ",
            "line": 7,
            "name": "I tap the first album in the list",
            "match": {
              "location": "features\\step_definitions\\albums.steps.js:35"
            },
            "result": {
              "status": "passed",
              "duration": 243135000
            }
          },
          {
            "arguments": [],
            "keyword": "And ",
            "line": 8,
            "name": "I tap the plus floating button",
            "match": {
              "location": "features\\step_definitions\\tracks_album.steps.js:4"
            },
            "result": {
              "status": "passed",
              "duration": 1002783499
            }
          },
          {
            "arguments": [],
            "keyword": "And ",
            "line": 9,
            "name": "I tap the add track option",
            "match": {
              "location": "features\\step_definitions\\tracks_album.steps.js:30"
            },
            "result": {
              "status": "passed",
              "duration": 1170755000
            }
          },
          {
            "arguments": [],
            "keyword": "And ",
            "line": 10,
            "name": "I enter the track name \"Christmas Tree\"",
            "match": {
              "location": "features\\step_definitions\\tracks_album.steps.js:56"
            },
            "result": {
              "status": "passed",
              "duration": 2116603400
            }
          },
          {
            "arguments": [],
            "keyword": "And ",
            "line": 11,
            "name": "I enter the track duration \"02:50\"",
            "match": {
              "location": "features\\step_definitions\\tracks_album.steps.js:81"
            },
            "result": {
              "status": "passed",
              "duration": 1576836600
            }
          },
          {
            "arguments": [],
            "keyword": "And ",
            "line": 12,
            "name": "I tap the save track button",
            "match": {
              "location": "features\\step_definitions\\tracks_album.steps.js:107"
            },
            "result": {
              "status": "passed",
              "duration": 600952199
            }
          },
          {
            "arguments": [],
            "keyword": "Then ",
            "line": 13,
            "name": "I should see the track added toast",
            "match": {
              "location": "features\\step_definitions\\tracks_album.steps.js:132"
            },
            "result": {
              "status": "passed",
              "duration": 735456500
            }
          },
          {
            "arguments": [],
            "keyword": "And ",
            "line": 14,
            "name": "I should see the track name \"Christmas Tree\" in the tracks list",
            "match": {
              "location": "features\\step_definitions\\tracks_album.steps.js:192"
            },
            "result": {
              "status": "passed",
              "duration": 3589800900
            }
          },
          {
            "keyword": "After",
            "hidden": true,
            "result": {
              "status": "passed",
              "duration": 1152039300
            }
          }
        ],
        "tags": [],
        "type": "scenario"
      }
    ],
    "id": "hu08---álbumes-lista-y-detalle",
    "line": 1,
    "keyword": "Feature",
    "name": "HU08 - Álbumes lista y detalle",
    "tags": [],
    "uri": "features\\tracks_album.feature"
  }
]